mazewright/__init__.py
mazewright/__main__.py
mazewright/maze.py
mazewright/solver.py
mazewright/visualize.py
mazewright/algorithms/__init__.py
mazewright/algorithms/backtracker.py
mazewright/algorithms/kruskal.py
mazewright/algorithms/prim.py
mazewright-0.2.0.dist-info/METADATA
mazewright-0.2.0.dist-info/WHEEL
mazewright-0.2.0.dist-info/entry_points.txt
mazewright-0.2.0.dist-info/top_level.txt
mazewright-0.2.0.dist-info/RECORD
