Metadata-Version: 2.4
Name: mazewright
Version: 0.2.0
Summary: A Python package for generating and visualizing mazes
Author-email: Sebastian Griego <sebastianngriego@gmail.com>
License: MIT
Requires-Python: >=3.10
Requires-Dist: matplotlib>=3.5.0
Provides-Extra: dev
Requires-Dist: pytest>=7.0.0; extra == "dev"
Requires-Dist: pytest-cov>=3.0.0; extra == "dev"
Requires-Dist: black>=22.0.0; extra == "dev"
Requires-Dist: ruff>=0.1.0; extra == "dev"
Requires-Dist: pre-commit>=2.20.0; extra == "dev"
